[
    {
        "text": "",
        "files": [
            {
                "id": "F048P9S4N9G",
                "mode": "hidden_by_limit"
            }
        ],
        "upload": false,
        "user": "USH01JEDQ",
        "display_as_bot": false,
        "type": "message",
        "ts": "1667082031.192589",
        "client_msg_id": "588CF177-038B-4054-849D-423016A46018",
        "thread_ts": "1667010600.811069",
        "parent_user_id": "U03B14DUZSA"
    },
    {
        "user": "USH01JEDQ",
        "type": "message",
        "ts": "1667082837.162179",
        "client_msg_id": "0EAA079D-C0A0-4F32-8C8C-DCCD95546BB0",
        "text": "<https:\/\/beyondloom.com\/blog\/peepoflil.html|https:\/\/beyondloom.com\/blog\/peepoflil.html>",
        "team": "T5TCAFTA9",
        "user_team": "T5TCAFTA9",
        "source_team": "T5TCAFTA9",
        "user_profile": {
            "avatar_hash": "854f96b690f5",
            "image_72": "https:\/\/avatars.slack-edge.com\/2023-12-17\/6370745671793_854f96b690f51d1266ee_72.png",
            "first_name": "Christopher",
            "real_name": "Christopher Galtenberg",
            "display_name": "Chris G",
            "team": "T5TCAFTA9",
            "name": "galtenberg",
            "is_restricted": false,
            "is_ultra_restricted": false
        },
        "thread_ts": "1667010600.811069",
        "parent_user_id": "U03B14DUZSA",
        "blocks": [
            {
                "type": "rich_text",
                "block_id": "zJP",
                "elements": [
                    {
                        "type": "rich_text_section",
                        "elements": [
                            {
                                "type": "link",
                                "url": "https:\/\/beyondloom.com\/blog\/peepoflil.html",
                                "text": "https:\/\/beyondloom.com\/blog\/peepoflil.html"
                            }
                        ]
                    }
                ]
            }
        ]
    },
    {
        "user": "USH01JEDQ",
        "type": "message",
        "ts": "1667082911.709109",
        "client_msg_id": "64004EC4-42E0-4D09-A5C3-2B51034A6D35",
        "text": "<https:\/\/beyondloom.com\/decker\/lil.html|https:\/\/beyondloom.com\/decker\/lil.html>",
        "team": "T5TCAFTA9",
        "user_team": "T5TCAFTA9",
        "source_team": "T5TCAFTA9",
        "user_profile": {
            "avatar_hash": "854f96b690f5",
            "image_72": "https:\/\/avatars.slack-edge.com\/2023-12-17\/6370745671793_854f96b690f51d1266ee_72.png",
            "first_name": "Christopher",
            "real_name": "Christopher Galtenberg",
            "display_name": "Chris G",
            "team": "T5TCAFTA9",
            "name": "galtenberg",
            "is_restricted": false,
            "is_ultra_restricted": false
        },
        "thread_ts": "1667010600.811069",
        "parent_user_id": "U03B14DUZSA",
        "blocks": [
            {
                "type": "rich_text",
                "block_id": "gSOw",
                "elements": [
                    {
                        "type": "rich_text_section",
                        "elements": [
                            {
                                "type": "link",
                                "url": "https:\/\/beyondloom.com\/decker\/lil.html",
                                "text": "https:\/\/beyondloom.com\/decker\/lil.html"
                            }
                        ]
                    }
                ]
            }
        ]
    }
]