[
    {
        "user": "U07BD7U4S4R",
        "type": "message",
        "ts": "1758719833.540169",
        "client_msg_id": "6d192e72-b672-4e14-bb94-6dec888388b2",
        "text": "I agree with most of <https:\/\/tonsky.me\/blog\/dsl\/>\nHowever, I think verbosity can be replaced\/achieved\/assisted by \"IDE integration\" to some degree, e.g. if IDE suggests would show, limit, and explain tokens I can use in curtain expression positions – tokens themselves could be short.",
        "team": "T5TCAFTA9",
        "user_team": "T5TCAFTA9",
        "source_team": "T5TCAFTA9",
        "user_profile": {
            "avatar_hash": "d0343f70ca57",
            "image_72": "https:\/\/avatars.slack-edge.com\/2024-07-04\/7377091009748_d0343f70ca57c18eeb41_72.png",
            "first_name": "misha",
            "real_name": "misha",
            "display_name": "misha",
            "team": "T5TCAFTA9",
            "name": "misha.akovantsev",
            "is_restricted": false,
            "is_ultra_restricted": false
        },
        "thread_ts": "1758605575.031369",
        "parent_user_id": "U07BD7U4S4R",
        "blocks": [
            {
                "type": "rich_text",
                "block_id": "anYgh",
                "elements": [
                    {
                        "type": "rich_text_section",
                        "elements": [
                            {
                                "type": "text",
                                "text": "I agree with most of "
                            },
                            {
                                "type": "link",
                                "url": "https:\/\/tonsky.me\/blog\/dsl\/"
                            },
                            {
                                "type": "text",
                                "text": "\nHowever, I think verbosity can be replaced\/achieved\/assisted by \"IDE integration\" to some degree, e.g. if IDE suggests would show, limit, and explain tokens I can use in curtain expression positions – tokens themselves could be short."
                            }
                        ]
                    }
                ]
            }
        ]
    }
]