[
    {
        "user": "UCUSW7WVD",
        "type": "message",
        "ts": "1696383712.458039",
        "client_msg_id": "92bd1e26-eef4-4aa4-830d-cb02ebc4f847",
        "text": "The Great Ptolemaic Smackdown\n\nThis series is utterly compelling: <https:\/\/web.archive.org\/web\/20140527202447\/http:\/\/tofspot.blogspot.com\/2013\/10\/the-great-ptolemaic-smackdown-table-of.html>",
        "team": "T5TCAFTA9",
        "user_team": "T5TCAFTA9",
        "source_team": "T5TCAFTA9",
        "user_profile": {
            "avatar_hash": "6e649a383cf8",
            "image_72": "https:\/\/avatars.slack-edge.com\/2019-07-14\/687915485201_6e649a383cf8f9e366e3_72.png",
            "first_name": "Kartik",
            "real_name": "Kartik Agaram",
            "display_name": "",
            "team": "T5TCAFTA9",
            "name": "ak",
            "is_restricted": false,
            "is_ultra_restricted": false
        },
        "blocks": [
            {
                "type": "rich_text",
                "block_id": "259FL",
                "elements": [
                    {
                        "type": "rich_text_section",
                        "elements": [
                            {
                                "type": "text",
                                "text": "The Great Ptolemaic Smackdown\n\nThis series is utterly compelling: "
                            },
                            {
                                "type": "link",
                                "url": "https:\/\/web.archive.org\/web\/20140527202447\/http:\/\/tofspot.blogspot.com\/2013\/10\/the-great-ptolemaic-smackdown-table-of.html"
                            }
                        ]
                    }
                ]
            }
        ]
    }
]